gopher_mcp/__init__.py
gopher_mcp/__main__.py
gopher_mcp/certificate_errors.py
gopher_mcp/client_certs.py
gopher_mcp/config.py
gopher_mcp/fingerprints.py
gopher_mcp/gemini_client.py
gopher_mcp/gemini_tls.py
gopher_mcp/gopher_client.py
gopher_mcp/models.py
gopher_mcp/security.py
gopher_mcp/security_policy.py
gopher_mcp/server.py
gopher_mcp/tofu.py
gopher_mcp/tools.py
gopher_mcp/utils.py
gopher_mcp-0.2.2.dist-info/METADATA
gopher_mcp-0.2.2.dist-info/WHEEL
gopher_mcp-0.2.2.dist-info/entry_points.txt
gopher_mcp-0.2.2.dist-info/licenses/LICENSE
gopher_mcp-0.2.2.dist-info/RECORD
