Metadata-Version: 2.4
Name: gopher-mcp
Version: 0.2.2
Summary: A cross-platform Model Context Protocol (MCP) server for browsing Gopher resources
Project-URL: Homepage, https://github.com/cameronrye/gopher-mcp
Project-URL: Documentation, https://cameronrye.github.io/gopher-mcp
Project-URL: Repository, https://github.com/cameronrye/gopher-mcp
Project-URL: Issues, https://github.com/cameronrye/gopher-mcp/issues
Project-URL: Changelog, https://github.com/cameronrye/gopher-mcp/blob/main/CHANGELOG.md
Author-email: Gopher MCP Team <team@gopher-mcp.dev>
Maintainer-email: Gopher MCP Team <team@gopher-mcp.dev>
License-Expression: MIT
License-File: LICENSE
Keywords: gopher,llm,mcp,model-context-protocol,protocol
Classifier: Development Status :: 4 - Beta
Classifier: Framework :: AsyncIO
Classifier: Intended Audience :: Developers
Classifier: Intended Audience :: System Administrators
Classifier: License :: OSI Approved :: MIT License
Classifier: Operating System :: OS Independent
Classifier: Programming Language :: Python :: 3
Classifier: Programming Language :: Python :: 3.11
Classifier: Programming Language :: Python :: 3.12
Classifier: Programming Language :: Python :: 3.13
Classifier: Topic :: Communications
Classifier: Topic :: Internet :: WWW/HTTP
Classifier: Topic :: Internet :: WWW/HTTP :: Browsers
Classifier: Topic :: Software Development :: Libraries :: Python Modules
Classifier: Topic :: System :: Networking
Classifier: Typing :: Typed
Requires-Python: >=3.11
Requires-Dist: anyio>=4.0.0
Requires-Dist: cryptography>=41.0.0
Requires-Dist: mcp>=1.0.0
Requires-Dist: pituophis>=1.0.0
Requires-Dist: pydantic-settings>=2.0.0
Requires-Dist: pydantic>=2.5.0
Requires-Dist: structlog>=23.2.0
Provides-Extra: dev
Requires-Dist: bandit>=1.7.5; extra == 'dev'
Requires-Dist: mypy>=1.7.0; extra == 'dev'
Requires-Dist: pre-commit>=3.5.0; extra == 'dev'
Requires-Dist: pytest-asyncio>=0.21.0; extra == 'dev'
Requires-Dist: pytest-cov>=4.1.0; extra == 'dev'
Requires-Dist: pytest-mock>=3.11.0; extra == 'dev'
Requires-Dist: pytest>=7.4.0; extra == 'dev'
Requires-Dist: ruff>=0.14.5; extra == 'dev'
Requires-Dist: safety<3.0.0,>=2.3.0; extra == 'dev'
Requires-Dist: twine>=4.0.0; extra == 'dev'
Requires-Dist: typer<0.21.0; extra == 'dev'
Provides-Extra: docs
Requires-Dist: mkdocs-autorefs>=0.5.0; extra == 'docs'
Requires-Dist: mkdocs-material>=9.4.0; extra == 'docs'
Requires-Dist: mkdocs>=1.5.0; extra == 'docs'
Requires-Dist: mkdocstrings[python]>=0.24.0; extra == 'docs'
Requires-Dist: pymdown-extensions>=10.0.0; extra == 'docs'
Provides-Extra: http
Requires-Dist: aiohttp>=3.9.0; extra == 'http'
Provides-Extra: test
Requires-Dist: coverage[toml]>=7.3.0; extra == 'test'
Requires-Dist: pytest-asyncio>=0.21.0; extra == 'test'
Requires-Dist: pytest-cov>=4.1.0; extra == 'test'
Requires-Dist: pytest-mock>=3.11.0; extra == 'test'
Requires-Dist: pytest>=7.4.0; extra == 'test'
